mosaik_components/pandapipes/__init__.py
mosaik_components/pandapipes/simulator.py
mosaik_pandapipes-0.1.0.dist-info/LICENSE
mosaik_pandapipes-0.1.0.dist-info/METADATA
mosaik_pandapipes-0.1.0.dist-info/WHEEL
mosaik_pandapipes-0.1.0.dist-info/RECORD
