Metadata-Version: 2.1
Name: mosaik-pandapipes
Version: 0.1.0
Summary: An adapter to connect mosaik to pandapipes
License: MIT
Author: Deborah Tolk
Author-email: mosaik@offis.de
Requires-Python: >=3.8,<4.0
Classifier: License :: OSI Approved :: MIT License
Classifier: Programming Language :: Python :: 3
Classifier: Programming Language :: Python :: 3.8
Classifier: Programming Language :: Python :: 3.9
Classifier: Programming Language :: Python :: 3.10
Classifier: Programming Language :: Python :: 3.11
Classifier: Programming Language :: Python :: 3.12
Requires-Dist: mosaik-api-v3 (>=3.0.4,<4.0.0)
Requires-Dist: pandapipes (>=0.8.5,<0.9.0)
